ez_address_parser/__init__.py
ez_address_parser/__main__.py
ez_address_parser/address_parser.py
ez_address_parser/constants.py
ez_address_parser/features.py
ez_address_parser/model
ez_address_parser/utils.py
ez_address_parser-0.2.5.dist-info/LICENSE
ez_address_parser-0.2.5.dist-info/METADATA
ez_address_parser-0.2.5.dist-info/WHEEL
ez_address_parser-0.2.5.dist-info/top_level.txt
ez_address_parser-0.2.5.dist-info/RECORD
