Metadata-Version: 2.1
Name: ez-address-parser
Version: 0.2.5
Summary: A parser for Canadian postal addresses
Author-email: Zeheng Li <imzehengl@gmail.com>
Maintainer-email: Zeheng Li <imzehengl@gmail.com>
Project-URL: repository, https://github.com/zehengl/ez-address-parser
Project-URL: homepage, https://zehengl.github.io/ez-address-parser/
Keywords: adress parser,Canadian
Classifier: Programming Language :: Python :: 3
Classifier: License :: OSI Approved :: MIT License
Classifier: Operating System :: OS Independent
Requires-Python: >=3.8
License-File: LICENSE
Requires-Dist: sklearn-crfsuite
Requires-Dist: numpy
